ppyget.py
ppyget-0.1.0.dist-info/WHEEL
ppyget-0.1.0.dist-info/METADATA
ppyget-0.1.0.dist-info/RECORD
