Metadata-Version: 2.1
Name: ppyget
Version: 0.1.0
Summary: pretty parallel yellow get - file downloader
Author: technillogue
Author-email: technillogue@gmail.com
Requires-Python: >=3.10,<4.0
Classifier: Programming Language :: Python :: 3
Classifier: Programming Language :: Python :: 3.10
Requires-Dist: aiohttp[speedups] (>=3.8.5,<4.0.0)
